pyemddf/__init__.py
pyemddf/emddf_int.jar
pyemddf/integrator.py
pyemddf/utils.py
pyemddf-1.3.0.dist-info/LICENSE
pyemddf-1.3.0.dist-info/METADATA
pyemddf-1.3.0.dist-info/WHEEL
pyemddf-1.3.0.dist-info/top_level.txt
pyemddf-1.3.0.dist-info/RECORD
