Metadata-Version: 2.1
Name: pyemddf
Version: 1.3.0
Summary: Bridge connecting python and java EMD-DF.
Home-page: UNKNOWN
Author: Manuel Pereira
Author-email: afonso.pereira4525@gmail.com
License: The MIT License
Platform: UNKNOWN
